pillow_lut/__init__.py
pillow_lut/generators.py
pillow_lut/loaders.py
pillow_lut/operations.py
pillow_lut-1.1.0.dist-info/licenses/LICENSE
pillow_lut-1.1.0.dist-info/METADATA
pillow_lut-1.1.0.dist-info/WHEEL
pillow_lut-1.1.0.dist-info/top_level.txt
pillow_lut-1.1.0.dist-info/RECORD
