Metadata-Version: 2.4
Name: pillow_lut
Version: 1.1.0
Summary: Lookup tables loading, manipulation and generation for Pillow library
Home-page: https://github.com/homm/pillow-lut-tools
Author: Aleksandr Karpinskii
Author-email: homm86@gmail.com
Classifier: Development Status :: 6 - Mature
Classifier: Topic :: Multimedia :: Graphics
Classifier: License :: OSI Approved :: MIT License
Classifier: Programming Language :: Python :: 3
Classifier: Programming Language :: Python :: 3.7
Classifier: Programming Language :: Python :: 3.8
Classifier: Programming Language :: Python :: 3.9
Classifier: Programming Language :: Python :: 3.10
Classifier: Programming Language :: Python :: 3.11
Classifier: Programming Language :: Python :: Implementation :: CPython
Classifier: Programming Language :: Python :: Implementation :: PyPy
License-File: LICENSE
Requires-Dist: pillow>=5.2.0
Dynamic: author
Dynamic: author-email
Dynamic: classifier
Dynamic: home-page
Dynamic: license-file
Dynamic: requires-dist
Dynamic: summary
